README.md
setup.py
PyCCAPT_Control.egg-info/PKG-INFO
PyCCAPT_Control.egg-info/SOURCES.txt
PyCCAPT_Control.egg-info/dependency_links.txt
PyCCAPT_Control.egg-info/entry_points.txt
PyCCAPT_Control.egg-info/namespace_packages.txt
PyCCAPT_Control.egg-info/not-zip-safe
PyCCAPT_Control.egg-info/requires.txt
PyCCAPT_Control.egg-info/top_level.txt
pyccapt/apt/__init__.py
pyccapt/apt/apt_tdc_roetdec.py
pyccapt/apt/apt_tdc_surface_consept.py
pyccapt/control_tools/__init__.py
pyccapt/control_tools/com_ports.py
pyccapt/control_tools/experiment_statistics.py
pyccapt/control_tools/hdf5_creator.py
pyccapt/control_tools/loggi.py
pyccapt/control_tools/read_files.py
pyccapt/control_tools/tof2mc_simple.py
pyccapt/control_tools/variables.py
pyccapt/devices/__init__.py
pyccapt/devices/camera.py
pyccapt/devices/edwards_tic.py
pyccapt/devices/email_send.py
pyccapt/devices/initialize_devices.py
pyccapt/devices/pfeiffer_gauges.py
pyccapt/devices/signal_generator.py
pyccapt/devices/tweet_send.py
pyccapt/devices_test/__init__.py
pyccapt/devices_test/camera.py
pyccapt/devices_test/counter.py
pyccapt/devices_test/drs.py
pyccapt/devices_test/gates.py
pyccapt/devices_test/serial_com_cryovac.py
pyccapt/devices_test/serial_com_edwards.py
pyccapt/devices_test/serial_com_pfeiffer.py
pyccapt/devices_test/serial_com_v_dc.py
pyccapt/devices_test/serial_com_v_p.py
pyccapt/devices_test/siglent_signal_generator.py
pyccapt/devices_test/tdc_roentec_t.py
pyccapt/devices_test/tdc_surface_concept_t_1.py
pyccapt/devices_test/tdc_surface_concept_t_2.py
pyccapt/drs/__init__.py
pyccapt/drs/drs.py
pyccapt/gui/__init__.py
pyccapt/gui/__main__.py
pyccapt/gui/gui_advance.py
pyccapt/gui/gui_simple.py
pyccapt/tdc_roentdec/__init__.py
pyccapt/tdc_roentdec/tdc_roentdec.py
pyccapt/tdc_surface_concept/__init__.py
pyccapt/tdc_surface_concept/scTDC.py
pyccapt/tdc_surface_concept/tdc_surface_consept.py